<annotation>
	<folder>dataset</folder>
	<filename>104.jpeg</filename>
	<path>D:\AI模型和环境\code\dataset\104.jpeg</path>
	<source>
		<database>Unknown</database>
	</source>
	<size>
		<width>2796</width>
		<height>1290</height>
		<depth>3</depth>
	</size>
	<segmented>0</segmented>
	<object>
		<name>op_bar</name>
		<pose>Unspecified</pose>
		<truncated>1</truncated>
		<difficult>0</difficult>
		<bndbox>
			<xmin>2493</xmin>
			<ymin>1</ymin>
			<xmax>2638</xmax>
			<ymax>1290</ymax>
		</bndbox>
	</object>
	<object>
		<name>seckill</name>
		<pose>Unspecified</pose>
		<truncated>1</truncated>
		<difficult>0</difficult>
		<bndbox>
			<xmin>1466</xmin>
			<ymin>2</ymin>
			<xmax>2406</xmax>
			<ymax>1290</ymax>
		</bndbox>
	</object>
	<object>
		<name>banner</name>
		<pose>Unspecified</pose>
		<truncated>1</truncated>
		<difficult>0</difficult>
		<bndbox>
			<xmin>1212</xmin>
			<ymin>7</ymin>
			<xmax>1461</xmax>
			<ymax>1290</ymax>
		</bndbox>
	</object>
	<object>
		<name>item</name>
		<pose>Unspecified</pose>
		<truncated>0</truncated>
		<difficult>0</difficult>
		<bndbox>
			<xmin>149</xmin>
			<ymin>10</ymin>
			<xmax>1080</xmax>
			<ymax>649</ymax>
		</bndbox>
	</object>
	<object>
		<name>item</name>
		<pose>Unspecified</pose>
		<truncated>0</truncated>
		<difficult>0</difficult>
		<bndbox>
			<xmin>101</xmin>
			<ymin>644</ymin>
			<xmax>1079</xmax>
			<ymax>1274</ymax>
		</bndbox>
	</object>
</annotation>
